netbox/__init__.py
netbox/constant.py
netbox/core.py
netbox/exception.py
netbox/helper.py
netbox/runner.py
netbox/version.py
netbox/wifi.py
netbox/scripts/__init__.py
netbox/scripts/command.py
netbox/tests/__init__.py
netbox/tests/test_netbox.py
netbox-0.0.2.dist-info/LICENSE
netbox-0.0.2.dist-info/METADATA
netbox-0.0.2.dist-info/WHEEL
netbox-0.0.2.dist-info/entry_points.txt
netbox-0.0.2.dist-info/top_level.txt
netbox-0.0.2.dist-info/RECORD
