Metadata-Version: 2.1
Name: netbox
Version: 0.0.2
Summary: A python simple and flexible CLI tool used to network testing.
Home-page: https://github.com/Hellboycc/netbox
Author: Hellboycc
Author-email: luoyingchuan1210@gmail.com
License: UNKNOWN
Keywords: CLI tool,Network,Software Testing
Platform: UNKNOWN
Classifier: Development Status :: 3 - Alpha
Classifier: Intended Audience :: Developers
Classifier: License :: OSI Approved :: MIT License
Classifier: Natural Language :: English
Classifier: Operating System :: OS Independent
Classifier: Programming Language :: Python
Classifier: Programming Language :: Python :: 3.10
Classifier: Topic :: Software Development :: Libraries
Requires-Python: >=3.7
License-File: LICENSE
